biz_mcp_server/__init__.py
biz_mcp_server/server.py
biz_mcp_server-0.1.0.dist-info/METADATA
biz_mcp_server-0.1.0.dist-info/WHEEL
biz_mcp_server-0.1.0.dist-info/entry_points.txt
biz_mcp_server-0.1.0.dist-info/RECORD
