Metadata-Version: 2.4
Name: biz-mcp-server
Version: 0.1.0
Summary: for work
Author-email: fritzprix <innocentevil0914@gmail.com>
Requires-Python: >=3.11
Requires-Dist: mcp>=1.2.1
